{
    "id": 508,
    "firstname": "Gisèle",
    "lastname": "Biémouret",
    "region": "Occitanie",
    "county": "Gers",
    "circumscription": 2,
    "job": "Assistante parlementaire",
    "group": "Socialistes et apparentés",
    "groupShort": "SOC",
    "slug": "gisele-biemouret",
    "votes": {
        "Scrutin public sur l'ensemble du projet de loi organique relatif au système universel de retraite (première lecture).": {
            "weight": 1,
            "vote": "Absent"
        },
        "Scrutin public sur l'ensemble de la proposition de loi pour une sécurité globale préservant les libertés (texte de la commission mixte paritaire).": {
            "weight": 1,
            "vote": "Absent"
        },
        "Scrutin public sur l'ensemble du projet de loi relatif à la bioéthique (lecture définitive). ": {
            "weight": 1,
            "vote": "Pour"
        },
        "Scrutin public sur l'ensemble du projet de loi de finances pour 2022 (lecture définitive). ": {
            "weight": 1,
            "vote": "Absent"
        }
    },
    "firstRoundResults": {
        "registered": 73682,
        "voted": 59637,
        "whites": 861,
        "void": 434,
        "candidates": {
            "Nathalie Arthaud": 269,
            "Fabien Roussel": 1432,
            "Emmanuel Macron": 14610,
            "Jean Lasalle": 5618,
            "Marine Le Pen": 13418,
            "Jean-Luc Mélenchon": 10078,
            "Anne Hidalgo": 1852,
            "Yannick Jadot": 2128,
            "Valérie Pécresse": 2660,
            "Phillipe Poutou": 368,
            "Nicolas Dupont-Aignan": 1241
        }
    }
}