[
    {
        "countyId": "ZN",
        "countyName": "Nouvelle-Calédonie",
        "villageId": 801,
        "villageName": "Belep",
        "circumscriptionNumber": 2,
        "cantonId": 2,
        "cantonName": "NORD - KONE (fictif)"
    },
    {
        "countyId": "ZN",
        "countyName": "Nouvelle-Calédonie",
        "villageId": 802,
        "villageName": "Boulouparis",
        "circumscriptionNumber": 2,
        "cantonId": 3,
        "cantonName": "SUD - NOUMEA (fictif)"
    },
    {
        "countyId": "ZN",
        "countyName": "Nouvelle-Calédonie",
        "villageId": 803,
        "villageName": "Bourail",
        "circumscriptionNumber": 2,
        "cantonId": 3,
        "cantonName": "SUD - NOUMEA (fictif)"
    },
    {
        "countyId": "ZN",
        "countyName": "Nouvelle-Calédonie",
        "villageId": 804,
        "villageName": "Canala",
        "circumscriptionNumber": 2,
        "cantonId": 2,
        "cantonName": "NORD - KONE (fictif)"
    },
    {
        "countyId": "ZN",
        "countyName": "Nouvelle-Calédonie",
        "villageId": 805,
        "villageName": "Dumbéa",
        "circumscriptionNumber": 2,
        "cantonId": 3,
        "cantonName": "SUD - NOUMEA (fictif)"
    },
    {
        "countyId": "ZN",
        "countyName": "Nouvelle-Calédonie",
        "villageId": 806,
        "villageName": "Farino",
        "circumscriptionNumber": 2,
        "cantonId": 3,
        "cantonName": "SUD - NOUMEA (fictif)"
    },
    {
        "countyId": "ZN",
        "countyName": "Nouvelle-Calédonie",
        "villageId": 807,
        "villageName": "Hienghène",
        "circumscriptionNumber": 2,
        "cantonId": 2,
        "cantonName": "NORD - KONE (fictif)"
    },
    {
        "countyId": "ZN",
        "countyName": "Nouvelle-Calédonie",
        "villageId": 808,
        "villageName": "Houailou",
        "circumscriptionNumber": 2,
        "cantonId": 2,
        "cantonName": "NORD - KONE (fictif)"
    },
    {
        "countyId": "ZN",
        "countyName": "Nouvelle-Calédonie",
        "villageId": 809,
        "villageName": "Ile des Pins",
        "circumscriptionNumber": 1,
        "cantonId": 3,
        "cantonName": "SUD - NOUMEA (fictif)"
    },
    {
        "countyId": "ZN",
        "countyName": "Nouvelle-Calédonie",
        "villageId": 810,
        "villageName": "Kaala-Gomen",
        "circumscriptionNumber": 2,
        "cantonId": 2,
        "cantonName": "NORD - KONE (fictif)"
    },
    {
        "countyId": "ZN",
        "countyName": "Nouvelle-Calédonie",
        "villageId": 811,
        "villageName": "Koné",
        "circumscriptionNumber": 2,
        "cantonId": 2,
        "cantonName": "NORD - KONE (fictif)"
    },
    {
        "countyId": "ZN",
        "countyName": "Nouvelle-Calédonie",
        "villageId": 812,
        "villageName": "Koumac",
        "circumscriptionNumber": 2,
        "cantonId": 2,
        "cantonName": "NORD - KONE (fictif)"
    },
    {
        "countyId": "ZN",
        "countyName": "Nouvelle-Calédonie",
        "villageId": 813,
        "villageName": "La Foa",
        "circumscriptionNumber": 2,
        "cantonId": 3,
        "cantonName": "SUD - NOUMEA (fictif)"
    },
    {
        "countyId": "ZN",
        "countyName": "Nouvelle-Calédonie",
        "villageId": 814,
        "villageName": "Lifou",
        "circumscriptionNumber": 1,
        "cantonId": 1,
        "cantonName": "ILES - LIFOU (fictif)"
    },
    {
        "countyId": "ZN",
        "countyName": "Nouvelle-Calédonie",
        "villageId": 815,
        "villageName": "Maré",
        "circumscriptionNumber": 1,
        "cantonId": 1,
        "cantonName": "ILES - LIFOU (fictif)"
    },
    {
        "countyId": "ZN",
        "countyName": "Nouvelle-Calédonie",
        "villageId": 816,
        "villageName": "Moindou",
        "circumscriptionNumber": 2,
        "cantonId": 3,
        "cantonName": "SUD - NOUMEA (fictif)"
    },
    {
        "countyId": "ZN",
        "countyName": "Nouvelle-Calédonie",
        "villageId": 817,
        "villageName": "Mont-Dore",
        "circumscriptionNumber": 2,
        "cantonId": 3,
        "cantonName": "SUD - NOUMEA (fictif)"
    },
    {
        "countyId": "ZN",
        "countyName": "Nouvelle-Calédonie",
        "villageId": 818,
        "villageName": "Nouméa",
        "circumscriptionNumber": 1,
        "cantonId": 3,
        "cantonName": "SUD - NOUMEA (fictif)"
    },
    {
        "countyId": "ZN",
        "countyName": "Nouvelle-Calédonie",
        "villageId": 819,
        "villageName": "Ouégoa",
        "circumscriptionNumber": 2,
        "cantonId": 2,
        "cantonName": "NORD - KONE (fictif)"
    },
    {
        "countyId": "ZN",
        "countyName": "Nouvelle-Calédonie",
        "villageId": 820,
        "villageName": "Ouvéa",
        "circumscriptionNumber": 1,
        "cantonId": 1,
        "cantonName": "ILES - LIFOU (fictif)"
    },
    {
        "countyId": "ZN",
        "countyName": "Nouvelle-Calédonie",
        "villageId": 821,
        "villageName": "Païta",
        "circumscriptionNumber": 2,
        "cantonId": 3,
        "cantonName": "SUD - NOUMEA (fictif)"
    },
    {
        "countyId": "ZN",
        "countyName": "Nouvelle-Calédonie",
        "villageId": 822,
        "villageName": "Poindimié",
        "circumscriptionNumber": 2,
        "cantonId": 2,
        "cantonName": "NORD - KONE (fictif)"
    },
    {
        "countyId": "ZN",
        "countyName": "Nouvelle-Calédonie",
        "villageId": 823,
        "villageName": "Ponérihouen",
        "circumscriptionNumber": 2,
        "cantonId": 2,
        "cantonName": "NORD - KONE (fictif)"
    },
    {
        "countyId": "ZN",
        "countyName": "Nouvelle-Calédonie",
        "villageId": 824,
        "villageName": "Pouébo",
        "circumscriptionNumber": 2,
        "cantonId": 2,
        "cantonName": "NORD - KONE (fictif)"
    },
    {
        "countyId": "ZN",
        "countyName": "Nouvelle-Calédonie",
        "villageId": 825,
        "villageName": "Pouembout",
        "circumscriptionNumber": 2,
        "cantonId": 2,
        "cantonName": "NORD - KONE (fictif)"
    },
    {
        "countyId": "ZN",
        "countyName": "Nouvelle-Calédonie",
        "villageId": 826,
        "villageName": "Poum",
        "circumscriptionNumber": 2,
        "cantonId": 2,
        "cantonName": "NORD - KONE (fictif)"
    },
    {
        "countyId": "ZN",
        "countyName": "Nouvelle-Calédonie",
        "villageId": 827,
        "villageName": "Poya",
        "circumscriptionNumber": 2,
        "cantonId": 2,
        "cantonName": "NORD - KONE (fictif)"
    },
    {
        "countyId": "ZN",
        "countyName": "Nouvelle-Calédonie",
        "villageId": 828,
        "villageName": "Sarraméa",
        "circumscriptionNumber": 2,
        "cantonId": 3,
        "cantonName": "SUD - NOUMEA (fictif)"
    },
    {
        "countyId": "ZN",
        "countyName": "Nouvelle-Calédonie",
        "villageId": 829,
        "villageName": "Thio",
        "circumscriptionNumber": 2,
        "cantonId": 3,
        "cantonName": "SUD - NOUMEA (fictif)"
    },
    {
        "countyId": "ZN",
        "countyName": "Nouvelle-Calédonie",
        "villageId": 830,
        "villageName": "Touho",
        "circumscriptionNumber": 2,
        "cantonId": 2,
        "cantonName": "NORD - KONE (fictif)"
    },
    {
        "countyId": "ZN",
        "countyName": "Nouvelle-Calédonie",
        "villageId": 831,
        "villageName": "Voh",
        "circumscriptionNumber": 2,
        "cantonId": 2,
        "cantonName": "NORD - KONE (fictif)"
    },
    {
        "countyId": "ZN",
        "countyName": "Nouvelle-Calédonie",
        "villageId": 832,
        "villageName": "Yaté",
        "circumscriptionNumber": 2,
        "cantonId": 3,
        "cantonName": "SUD - NOUMEA (fictif)"
    },
    {
        "countyId": "ZN",
        "countyName": "Nouvelle-Calédonie",
        "villageId": 833,
        "villageName": "Kouaoua",
        "circumscriptionNumber": 2,
        "cantonId": 2,
        "cantonName": "NORD - KONE (fictif)"
    }
]