{
    "countyId": 25,
    "number": 4,
    "name": "Doubs",
    "candidates": [
        {
            "id": "642724",
            "lastname": "Barbier",
            "firstname": "Frédéric",
            "slug": "frederic-barbier",
            "gender": "H",
            "birthday": "1960-08-30",
            "birthplace": "Audincourt (Doubs)",
            "county": "Doubs",
            "countyId": "25",
            "circumscription": 4,
            "mandateStart": "2017-06-21",
            "group": "La République en Marche",
            "groupShort": "LREM",
            "job": "Cadre en entreprise",
            "votes": [],
            "scandals": [],
            "presence": {
                "weeksActive": 146,
                "reports": 2,
                "proposals": 0,
                "proposalsSupported": 93,
                "amendments": 15,
                "amendmentsSupported": 2479,
                "amendmentsAdopted": 1000,
                "commissionsAttended": 193,
                "commissionInterventions": 76,
                "hemicycleInterventions": 37,
                "hemicycleShortInterventions": 0,
                "questionsWritten": 96,
                "questionsOral": 5
            },
            "opposedGovernment": 0,
            "supportedGovernment": 0,
            "governmentLaws": 0
        },
        {
            "firstname": "Mathieu",
            "lastname": "Bloch",
            "group": "Les Républicains",
            "groupShort": "LR",
            "gender": "H",
            "noPicture": true
        },
        {
            "firstname": "Brigitte",
            "lastname": "Cottier",
            "group": "La France Insoumise",
            "groupShort": "LFI",
            "gender": "F",
            "noPicture": true
        },
        {
            "firstname": "Géraldine",
            "lastname": "Palenciano",
            "group": "Rassemblement National",
            "groupShort": "RN",
            "gender": "F",
            "noPicture": true
        },
        {
            "firstname": "Michel",
            "lastname": "Treppo",
            "group": "Lutte ouvrière",
            "groupShort": "LO",
            "gender": "H",
            "noPicture": true
        },
        {
            "firstname": "Philippe",
            "lastname": "Vourron",
            "group": "Reconquête",
            "groupShort": "R",
            "gender": "H",
            "noPicture": true
        }
    ]
}