{
    "countyId": "44",
    "number": 10,
    "name": "Loire-Atlantique",
    "results": {
        "2017": {
            "firstRound": {
                "registered": 123304,
                "voted": 99436,
                "whites": 1774,
                "expressed": 96965,
                "void": 697,
                "candidates": {
                    "Nathalie Arthaud": 558,
                    "Fabien Roussel": 1975,
                    "Emmanuel Macron": 34827,
                    "Jean Lasalle": 2366,
                    "Marine Le Pen": 16784,
                    "Jean-Luc Mélenchon": 18999,
                    "Anne Hidalgo": 2111,
                    "Yannick Jadot": 7494,
                    "Valérie Pécresse": 4603,
                    "Phillipe Poutou": 788,
                    "Nicolas Dupont-Aignan": 1831,
                    "Eric Zemmour": 4629
                }
            },
            "secondRound": {
                "registered": 123363,
                "voted": 98661,
                "whites": 6628,
                "expressed": 89824,
                "void": 2209,
                "candidates": {
                    "Emmanuel Macron": 63510,
                    "Marine Le Pen": 26314
                }
            }
        },
        "2022": {
            "firstRound": {
                "registered": 123757,
                "voted": 63838,
                "whites": 1000,
                "void": 479,
                "expressed": 62359
            }
        }
    },
    "current": {
        "id": "607193",
        "lastname": "Errante",
        "firstname": "Sophie",
        "current": true,
        "slug": "sophie-errante",
        "gender": "F",
        "birthday": "1971-07-22",
        "birthplace": "Nantes (Loire-Atlantique)",
        "county": "Loire-Atlantique",
        "countyId": "44",
        "circumscription": 10,
        "mandateStart": "2017-06-21",
        "groupShort": "LREM",
        "party": "La République en Marche",
        "partyShort": "LREM",
        "job": "Industriel-Chef d'entreprise",
        "votes": [],
        "scandals": [],
        "presence": {
            "weeksActive": 101,
            "reports": 1,
            "proposals": 0,
            "proposalsSupported": 62,
            "amendments": 12,
            "amendmentsSupported": 1661,
            "amendmentsAdopted": 1035,
            "commissionsAttended": 106,
            "commissionInterventions": 84,
            "hemicycleInterventions": 9,
            "hemicycleShortInterventions": 21,
            "questionsWritten": 5,
            "questionsOral": 1
        },
        "opposedGovernment": 0,
        "supportedGovernment": 0,
        "governmentLaws": 0
    },
    "candidates": [
        {
            "lastname": "GARDAIR",
            "firstname": "Emmanuèle",
            "gender": "F",
            "nuance": "DXG",
            "nuanceComputed": "LO",
            "party": "Lutte ouvrière",
            "partyShort": "Lutte ouvrière",
            "noPartyImage": true,
            "candidate": true,
            "firstRound": 572
        },
        {
            "lastname": "LEGER",
            "firstname": "Sabine",
            "gender": "F",
            "nuance": "REC",
            "nuanceComputed": "Rec.",
            "party": "Reconquête !",
            "partyShort": "REC",
            "candidate": true,
            "firstRound": 1979
        },
        {
            "lastname": "LEMPERNESSE",
            "firstname": "Florence",
            "gender": "F",
            "nuance": "DSV",
            "nuanceComputed": "DLF",
            "party": "Debout la France",
            "partyShort": "DLF",
            "noPartyImage": true,
            "candidate": true,
            "firstRound": 935
        },
        {
            "lastname": "BANNWARTH",
            "firstname": "Geneviève",
            "gender": "F",
            "nuance": "RN",
            "nuanceComputed": "RN",
            "party": "Rassemblement national",
            "partyShort": "RN",
            "candidate": true,
            "firstRound": 7011
        },
        {
            "lastname": "SAICHE",
            "firstname": "Malika",
            "gender": "F",
            "nuance": "ECO",
            "nuanceComputed": "Anim.",
            "party": "Parti animaliste",
            "partyShort": "PA",
            "candidate": true,
            "firstRound": 647
        },
        {
            "lastname": "CAILLETEAU",
            "firstname": "Bruno",
            "gender": "H",
            "nuance": "FI",
            "nuanceComputed": "LFI-Nupes",
            "party": "La France insoumise",
            "partyShort": "LFI",
            "candidate": true,
            "firstRound": 18699
        },
        {
            "lastname": "ERRANTE",
            "firstname": "Sophie",
            "gender": "F",
            "nuance": "ENS",
            "nuanceComputed": "LRM-Ensemble",
            "party": "La République en marche",
            "partyShort": "LREM",
            "candidate": true,
            "firstRound": 19638
        },
        {
            "lastname": "LUQUIAU",
            "firstname": "Charlotte",
            "gender": "F",
            "nuance": "LR",
            "nuanceComputed": "LR",
            "party": "Les Républicains",
            "partyShort": "LR",
            "candidate": true,
            "firstRound": 9377
        },
        {
            "lastname": "BONAMY",
            "firstname": "Guillaume",
            "gender": "H",
            "nuance": "DIV",
            "nuanceComputed": "div.",
            "party": "divers inclassable",
            "partyShort": "divers inclassable",
            "noPartyImage": true,
            "candidate": true,
            "firstRound": 1404
        },
        {
            "lastname": "CHÉNEAU",
            "firstname": "Philippe",
            "gender": "H",
            "nuance": "DVD",
            "nuanceComputed": "div. d.",
            "party": "divers droite",
            "partyShort": "divers droite",
            "noPartyImage": true,
            "candidate": true,
            "firstRound": 926
        },
        {
            "lastname": "DANA",
            "firstname": "Richard",
            "gender": "H",
            "nuance": "DVD",
            "nuanceComputed": "div.",
            "party": "divers inclassable",
            "partyShort": "divers inclassable",
            "noPartyImage": true,
            "candidate": true,
            "firstRound": 695
        },
        {
            "lastname": "CHÉNEAU",
            "firstname": "Maxime",
            "gender": "H",
            "nuance": "REG",
            "nuanceComputed": "rég.",
            "party": "régionalistes",
            "partyShort": "régionalistes",
            "noPartyImage": true,
            "candidate": true,
            "firstRound": 476
        }
    ]
}