{
    "countyId": "59",
    "number": 5,
    "name": "Nord",
    "results": {
        "2017": {
            "firstRound": {
                "registered": 101258,
                "voted": 76585,
                "whites": 1155,
                "expressed": 75028,
                "void": 402,
                "candidates": {
                    "Nathalie Arthaud": 442,
                    "Fabien Roussel": 2361,
                    "Emmanuel Macron": 22344,
                    "Jean Lasalle": 1299,
                    "Marine Le Pen": 21342,
                    "Jean-Luc Mélenchon": 13752,
                    "Anne Hidalgo": 1223,
                    "Yannick Jadot": 3560,
                    "Valérie Pécresse": 2570,
                    "Phillipe Poutou": 494,
                    "Nicolas Dupont-Aignan": 1269,
                    "Eric Zemmour": 4372
                }
            },
            "secondRound": {
                "registered": 101274,
                "voted": 77130,
                "whites": 4371,
                "expressed": 71284,
                "void": 1475,
                "candidates": {
                    "Emmanuel Macron": 39335,
                    "Marine Le Pen": 31949
                }
            }
        },
        "2022": {
            "firstRound": {
                "registered": 101579,
                "voted": 49930,
                "whites": 797,
                "void": 233,
                "expressed": 48900
            }
        }
    },
    "current": {
        "id": "267200",
        "lastname": "Huyghe",
        "firstname": "Sébastien",
        "current": true,
        "slug": "sebastien-huyghe",
        "gender": "H",
        "birthday": "1969-10-25",
        "birthplace": "Béthune (Pas-de-Calais)",
        "county": "Nord",
        "countyId": "59",
        "circumscription": 5,
        "mandateStart": "2017-06-21",
        "groupShort": "LR",
        "party": "Les Républicains",
        "partyShort": "LR",
        "job": "Notaire",
        "votes": [],
        "scandals": [],
        "presence": {
            "weeksActive": 147,
            "reports": 1,
            "proposals": 8,
            "proposalsSupported": 91,
            "amendments": 179,
            "amendmentsSupported": 3114,
            "amendmentsAdopted": 123,
            "commissionsAttended": 173,
            "commissionInterventions": 113,
            "hemicycleInterventions": 297,
            "hemicycleShortInterventions": 107,
            "questionsWritten": 74,
            "questionsOral": 8
        },
        "opposedGovernment": 0,
        "supportedGovernment": 0,
        "governmentLaws": 0
    },
    "candidates": [
        {
            "lastname": "CATTEAU",
            "firstname": "Victor",
            "gender": "H",
            "nuance": "RN",
            "nuanceComputed": "RN",
            "party": "Rassemblement national",
            "partyShort": "RN",
            "candidate": true,
            "firstRound": 12211
        },
        {
            "lastname": "STOFFEL",
            "firstname": "Manon",
            "gender": "F",
            "nuance": "ECO",
            "nuanceComputed": "Anim.",
            "party": "Parti animaliste",
            "partyShort": "PA",
            "candidate": true,
            "firstRound": 1498
        },
        {
            "lastname": "CAUDERLIER",
            "firstname": "Frédéric",
            "gender": "H",
            "nuance": "ENS",
            "nuanceComputed": "LRM-Ensemble",
            "party": "La République en marche",
            "partyShort": "LREM",
            "candidate": true,
            "firstRound": 12012
        },
        {
            "lastname": "DELNESTE",
            "firstname": "Ophélie",
            "gender": "F",
            "nuance": "FI",
            "nuanceComputed": "LFI-Nupes",
            "party": "La France insoumise",
            "partyShort": "LFI",
            "candidate": true,
            "firstRound": 12213
        },
        {
            "lastname": "DENNEQUIN",
            "firstname": "Pierrick",
            "gender": "H",
            "nuance": "DSV",
            "nuanceComputed": "Pat.",
            "party": "Les Patriotes",
            "partyShort": "Les Patriotes",
            "noPartyImage": true,
            "candidate": true,
            "firstRound": 589
        },
        {
            "lastname": "SION",
            "firstname": "Hugues",
            "gender": "H",
            "nuance": "REC",
            "nuanceComputed": "Rec.",
            "party": "Reconquête !",
            "partyShort": "REC",
            "candidate": true,
            "firstRound": 1196
        },
        {
            "lastname": "HUYGHE",
            "firstname": "Sébastien",
            "gender": "H",
            "nuance": "LR",
            "nuanceComputed": "LR",
            "party": "Les Républicains",
            "partyShort": "LR",
            "candidate": true,
            "firstRound": 8562
        },
        {
            "lastname": "DUBOIS",
            "firstname": "Luc",
            "gender": "H",
            "nuance": "DXG",
            "nuanceComputed": "LO",
            "party": "Lutte ouvrière",
            "partyShort": "Lutte ouvrière",
            "noPartyImage": true,
            "candidate": true,
            "firstRound": 619
        }
    ]
}