{
    "countyId": 59,
    "number": 4,
    "name": "Nord",
    "results": {
        "firstRound": {
            "registered": 100845,
            "voted": 74482,
            "whites": 947,
            "expressed": 73163,
            "void": 372,
            "candidates": {
                "Nathalie Arthaud": 316,
                "Fabien Roussel": 1690,
                "Emmanuel Macron": 26522,
                "Jean Lasalle": 1156,
                "Marine Le Pen": 13218,
                "Jean-Luc Mélenchon": 15008,
                "Anne Hidalgo": 1172,
                "Yannick Jadot": 4655,
                "Valérie Pécresse": 3359,
                "Phillipe Poutou": 448,
                "Nicolas Dupont-Aignan": 1087,
                "Eric Zemmour": 4532
            }
        }
    },
    "candidates": [
        {
            "firstname": "Fatima",
            "lastname": "Abdellaoui",
            "group": "Lutte ouvrière",
            "groupShort": "LO",
            "gender": "F",
            "noPicture": true
        },
        {
            "firstname": "Gauthier",
            "lastname": "Boullet",
            "group": "Parti animaliste",
            "groupShort": "PA",
            "gender": "H",
            "noPicture": true
        },
        {
            "firstname": "Octave",
            "lastname": "Delepiere",
            "group": "Europe, Ecologie, les Verts",
            "groupShort": "EELV",
            "gender": "H",
            "noPicture": true
        },
        {
            "firstname": "Ewann",
            "lastname": "Gavard",
            "group": "Parti pirate",
            "groupShort": "PP",
            "gender": "H",
            "noPicture": true
        },
        {
            "firstname": "Sébastien",
            "lastname": "Leblanc",
            "group": "Les Républicains",
            "groupShort": "LR",
            "gender": "H",
            "noPicture": true
        },
        {
            "id": "720446",
            "lastname": "Liso",
            "firstname": "Brigitte",
            "slug": "brigitte-liso",
            "gender": "F",
            "birthday": "1959-07-29",
            "birthplace": "Lille (Nord)",
            "county": "Nord",
            "countyId": "59",
            "circumscription": 4,
            "mandateStart": "2017-06-21",
            "group": "La République en Marche",
            "groupShort": "LREM",
            "job": "Commerçant",
            "votes": [],
            "scandals": [],
            "presence": {
                "weeksActive": 155,
                "reports": 2,
                "proposals": 0,
                "proposalsSupported": 67,
                "amendments": 42,
                "amendmentsSupported": 1784,
                "amendmentsAdopted": 979,
                "commissionsAttended": 233,
                "commissionInterventions": 46,
                "hemicycleInterventions": 53,
                "hemicycleShortInterventions": 10,
                "questionsWritten": 72,
                "questionsOral": 9
            },
            "opposedGovernment": 0,
            "supportedGovernment": 0,
            "governmentLaws": 0
        },
        {
            "firstname": "Patricia",
            "lastname": "Plancke",
            "group": "Rassemblement National",
            "groupShort": "RN",
            "gender": "F",
            "noPicture": true
        }
    ]
}