{
    "countyId": 69,
    "number": 5,
    "name": "Rhône",
    "candidates": [
        {
            "id": "721336",
            "lastname": "Brocard",
            "firstname": "Blandine",
            "slug": "blandine-brocard",
            "gender": "F",
            "birthday": "1981-11-03",
            "birthplace": "Strasbourg (Bas-Rhin)",
            "county": "Rhône",
            "countyId": "69",
            "circumscription": 5,
            "mandateStart": "2017-06-21",
            "group": "Mouvement Démocrate",
            "groupShort": "MODEM",
            "job": "Employée (secteur privé)",
            "votes": [],
            "scandals": [],
            "presence": {
                "weeksActive": 162,
                "reports": 0,
                "proposals": 0,
                "proposalsSupported": 63,
                "amendments": 255,
                "amendmentsSupported": 3042,
                "amendmentsAdopted": 1072,
                "commissionsAttended": 257,
                "commissionInterventions": 110,
                "hemicycleInterventions": 214,
                "hemicycleShortInterventions": 135,
                "questionsWritten": 20,
                "questionsOral": 9
            },
            "opposedGovernment": 0,
            "supportedGovernment": 0,
            "governmentLaws": 0
        },
        {
            "firstname": "Amaël",
            "lastname": "Doux",
            "group": "Parti pirate",
            "groupShort": "PP",
            "gender": "H",
            "noPicture": true
        },
        {
            "firstname": "Yves",
            "lastname": "Duigou",
            "group": "Rassemblement National",
            "groupShort": "RN",
            "gender": "H",
            "noPicture": true
        },
        {
            "firstname": "Bastien",
            "lastname": "Joint",
            "group": "Les Républicains",
            "groupShort": "LR",
            "gender": "H",
            "noPicture": true
        },
        {
            "firstname": "Julie",
            "lastname": "Kabil",
            "group": "Parti animaliste",
            "groupShort": "PA",
            "gender": "F",
            "noPicture": true
        },
        {
            "firstname": "Fabrice",
            "lastname": "Mateucci",
            "group": "Parti Socialiste",
            "groupShort": "PS",
            "gender": "H",
            "noPicture": true
        },
        {
            "firstname": "Hélène",
            "lastname": "Rivière",
            "group": "Lutte ouvrière",
            "groupShort": "LO",
            "gender": "F",
            "noPicture": true
        }
    ]
}